macrostrat/package_tools/__init__.py
macrostrat/package_tools/dependencies.py
macrostrat/package_tools/install.py
macrostrat/package_tools/publish.py
macrostrat_package_tools-1.1.2.dist-info/METADATA
macrostrat_package_tools-1.1.2.dist-info/WHEEL
macrostrat_package_tools-1.1.2.dist-info/entry_points.txt
macrostrat_package_tools-1.1.2.dist-info/RECORD
